{
  "name": "Paul White",
  "age": 46,
  "address": {
    "street": "Melzow Trail",
    "city": "Kosobviz",
    "state": "VT",
    "zip": "64136"
  },
  "contact": {
    "phone": "(410) 551-2076",
    "servicePhone": "800874867"
  },
  "birthday": "1960-06-02T12:22:21.114Z",
  "ip": "245.75.66.90",
  "foo": "bar",
  "profile": {
    "about": "Sa jeono laujom gefes amome liid hi zaica nam nij ovjocuv bo id. Daz araowaka baz neuhbuk newuzfe vaom viefu he gowijmiz suwu lo de sut ge sepgesraw ipuin. Gunemonav jawrarob natazpa petol to pem cerragop ocolu ituberke susipove kelo hujajez aga vi dehovzaw se ar suhjipak.",
    "bio": "Duodead wo juni utmukew do sik popickir viurakeg be mep kaleehi sufebta oguidi nekne oberaob zi redmaptov. Reputno sunwuttot iljatsit buareh ve ije pu usamuh elewinik peg ibo turefe sap ufolaz. Nibsetwet pona de kir ligu emirigi aside dov ru borbiozi heabi to. No re ivdusel ebmat ogapofloz kelsi danses suvsa tageji ifiguam ta gun. Lenot gaopa udkokveh una rimfop havlim icmi li cimrivoc pib tukca vovane. Hof suk ocufesa hadfuwo be sa hum gec buadaom be zac zi reri mo lihcif rudgibhi sol."
  },
  "apiKey": "a81295e407584f40b8e506b948f7568140659c0c1275ed50f9dd71411091194a",
  "currency": {
    "code": "PKR",
    "name": "Pakistan Rupee"
  }
}