{
  "name": "Rosalie Mason",
  "age": 38,
  "address": {
    "street": "Devazi Parkway",
    "city": "Ojivucva",
    "state": "AZ",
    "zip": "60325"
  },
  "contact": {
    "phone": "(221) 309-2197",
    "servicePhone": "800733557"
  },
  "birthday": "1974-05-24T21:58:02.302Z",
  "ip": "234.55.50.139",
  "foo": "bar",
  "profile": {
    "about": "Otesazufa ripro lebagemu lostufdad rukowot onbolhod ta ul gig rerusowi zim ufoelivo. Fuvjo cak kimcuwba sib vohrucpeh nozarfes ujo imuzeke elofo fec gunez peumoami lusuf wurelid bowe of pi inicnut. Duiza wonor noh oloso geza fi kokohvom diboguf pezdalusi pajo min si ideabsu fanitep. Wobko vovlim obievebu cibzijfe efpu itazheh nepsoh wosake dez po birbah piz hudem. Co aro gemolo holbepo afa ko wipkeho ze suer idobugpor ir vocjahbi uknowceb tovcuhruw hubbop. Uwjezled bi ir wekcaf lippav ilacewab pujtep es hup ihuvomzim jadzaf fofbursav. Wesjesti inonit pineg cim sirpeaba hedjap biug lutha buuforo tas wicrovva gareliet onokosu jiof cevef ho ozesihuf hivac.",
    "bio": "Wocajcuk ohu hemap zibel rizjo ab edcuscib taiw jor rapusen upo hudi dijarefig ubunowa ko ugeapize tedvuledo cidrezar. Onsa mif efi petwab tisu fuwde epuga nuivmus rigoap uvlizeb canvulir bas cukeulu gaetuwe. Fuisicu cag tiajse wegzunlev wozebluw wemoze ufasu devew zen ginadori dik cighon nurepe ke ke ger ijpijin oho. Hidaneen jej otlek hokloh peme muzjeroh tuzfih si hosebu dibepeicu hovi tusse ruki. Fazaw so saoklu towwumif ofahoco pid ahoiwava hubsecig lohdawlev jizwitor mab pe."
  },
  "apiKey": "21b1cfcce1b57b9b9d68e1476cc684c9106402d16fc31b28676157b9cd3d9eef",
  "currency": {
    "code": "HUF",
    "name": "Hungary Forint"
  }
}